unqdantic/__init__.py
unqdantic/core.py
unqdantic/expression.py
unqdantic/meta.py
unqdantic/models.py
unqdantic/types.py
unqdantic/utils.py
unqdantic-0.2.0.dist-info/LICENSE
unqdantic-0.2.0.dist-info/METADATA
unqdantic-0.2.0.dist-info/WHEEL
unqdantic-0.2.0.dist-info/RECORD
