Metadata-Version: 2.1
Name: unqdantic
Version: 0.2.0
Summary: A embedded NoSQL database ODM based on UnQLite.
Home-page: https://github.com/CMHopeSunshine/unqdantic
License: MIT
Author: CMHopeSunshine
Author-email: 277073121@qq.com
Requires-Python: >=3.8,<4.0
Classifier: License :: OSI Approved :: MIT License
Classifier: Programming Language :: Python :: 3
Classifier: Programming Language :: Python :: 3.8
Classifier: Programming Language :: Python :: 3.9
Classifier: Programming Language :: Python :: 3.10
Classifier: Programming Language :: Python :: 3.11
Classifier: Programming Language :: Python :: 3.12
Requires-Dist: pydantic (>=1.10.10,<2.0.0)
Requires-Dist: unqlite (>=0.9.6,<0.10.0)
Project-URL: Repository, https://github.com/CMHopeSunshine/unqdantic.git
